[
  {
    "id": "107fbcb3-1482-4e47-8c2d-97056931fc6d",
    "data": [
      {
        "text": "What dietary changes are good for PCOS?",
        "userDefined": false
      }
    ],
    "isTemplate": false,
    "count": 0,
    "lang": "en",
    "updated": 0
  },
  {
    "id": "bc864122-bc24-4525-8923-5a1c3d7f5133",
    "data": [
      {
        "text": "What nutrition plan works best for PCOS?",
        "userDefined": false
      }
    ],
    "isTemplate": false,
    "count": 0,
    "lang": "en",
    "updated": 0
  },
  {
    "id": "8a01810f-51a3-45af-a2ec-86fd6b3593b3",
    "data": [
      {
        "text": "Are there specific foods that help with PCOS?",
        "userDefined": false
      }
    ],
    "isTemplate": false,
    "count": 0,
    "lang": "en",
    "updated": 0
  },
  {
    "id": "c6ea113f-a63a-4cac-a25b-49c90cf2efd1",
    "data": [
      {
        "text": "What\u0027s a PCOS-friendly diet?",
        "userDefined": false
      }
    ],
    "isTemplate": false,
    "count": 0,
    "lang": "en",
    "updated": 0
  },
  {
    "id": "759054fa-c2cb-4b34-96ea-f5099efbf5ce",
    "data": [
      {
        "text": "How should I eat to manage PCOS?",
        "userDefined": false
      }
    ],
    "isTemplate": false,
    "count": 0,
    "lang": "en",
    "updated": 0
  },
  {
    "id": "ff863b6a-3aab-402f-a271-5a9dc231daed",
    "data": [
      {
        "text": "What type of diet is helpful for PCOS?",
        "userDefined": false
      }
    ],
    "isTemplate": false,
    "count": 0,
    "lang": "en",
    "updated": 0
  },
  {
    "id": "73f5dc6d-cf96-4111-a247-d0abaefc93a2",
    "data": [
      {
        "text": "Is there a recommended meal plan for PCOS?",
        "userDefined": false
      }
    ],
    "isTemplate": false,
    "count": 0,
    "lang": "en",
    "updated": 0
  },
  {
    "id": "45614675-8349-4f59-bddb-841427df6e87",
    "data": [
      {
        "text": "What foods are best for PCOS?",
        "userDefined": false
      }
    ],
    "isTemplate": false,
    "count": 0,
    "lang": "en",
    "updated": 0
  },
  {
    "id": "ba083b34-aa9b-4f27-9492-55a3057df139",
    "data": [
      {
        "text": "Can you suggest a good diet for PCOS?",
        "userDefined": false
      }
    ],
    "isTemplate": false,
    "count": 0,
    "lang": "en",
    "updated": 0
  },
  {
    "id": "8c7b5e83-a561-4564-b231-d9fd33649ba6",
    "data": [
      {
        "text": "What should I eat if I have PCOS?",
        "userDefined": false
      }
    ],
    "isTemplate": false,
    "count": 0,
    "lang": "en",
    "updated": 0
  },
  {
    "id": "7d830b50-a30f-4385-83eb-e3694ab20798",
    "data": [
      {
        "text": "What kind of diet helps with PCOS?",
        "userDefined": false
      }
    ],
    "isTemplate": false,
    "count": 0,
    "lang": "en",
    "updated": 0
  }
]